LightGeometry/__init__.py
LightGeometry/geometry.py
lightgeometry-1.0.1.dist-info/licenses/LICENSE.txt
lightgeometry-1.0.1.dist-info/METADATA
lightgeometry-1.0.1.dist-info/WHEEL
lightgeometry-1.0.1.dist-info/top_level.txt
lightgeometry-1.0.1.dist-info/RECORD
