Metadata-Version: 2.4
Name: LightGeometry
Version: 1.0.1
Summary: Light geometry library with essential function
Author-email: Cristiano <cristianoferrara.2006@gmail.com>
Keywords: python,library,geometry,math
Classifier: Programming Language :: Python :: 3
Classifier: License :: OSI Approved :: MIT License
Classifier: Operating System :: OS Independent
Requires-Python: >=3.9
License-File: LICENSE.txt
Dynamic: license-file
